LICENSE
MANIFEST.in
README.md
README.rst
setup.py
test/__init__.py
test/test_idseqs_to_mask.py
torch_tweaks/__init__.py
torch_tweaks/idseqs_to_mask.py
torch_tweaks.egg-info/PKG-INFO
torch_tweaks.egg-info/SOURCES.txt
torch_tweaks.egg-info/dependency_links.txt
torch_tweaks.egg-info/requires.txt
torch_tweaks.egg-info/top_level.txt
torch_tweaks.egg-info/zip-safe