Metadata-Version: 1.2
Name: torch-tweaks
Version: 0.1.2
Summary: Utility functions for PyTorch.
Home-page: http://github.com/ulf1/torch-tweaks
Author: Ulf Hamster
Author-email: 554c46@gmail.com
License: Apache License 2.0
Platform: UNKNOWN
Requires-Python: >=3.6
